odim/__init__.py
odim/basesignals.py
odim/dependencies.py
odim/dynmodels.py
odim/helper.py
odim/hook_types.py
odim/model_factory.py
odim/mongo.py
odim/mysql.py
odim/router.py
odim-0.1.33.dist-info/LICENSE
odim-0.1.33.dist-info/METADATA
odim-0.1.33.dist-info/WHEEL
odim-0.1.33.dist-info/top_level.txt
odim-0.1.33.dist-info/RECORD
