Metadata-Version: 2.1
Name: odim
Version: 0.1.33
Summary: Simple Python ORM/ODM specifically designed to be used with Pydantic and FastAPI 
Home-page: https://github.com/belda/odim
Author: Belda
Author-email: jakub.belescak@centrum.cz
License: UNKNOWN
Platform: UNKNOWN
Classifier: Programming Language :: Python :: 3
Classifier: License :: OSI Approved :: MIT License
Classifier: Operating System :: OS Independent
Requires-Python: >=3.6
Requires-Dist: pydantic
Requires-Dist: nest-asyncio
